django_pgsql_interval_field-0.9.4.dist-info/DESCRIPTION.rst
django_pgsql_interval_field-0.9.4.dist-info/METADATA
django_pgsql_interval_field-0.9.4.dist-info/metadata.json
django_pgsql_interval_field-0.9.4.dist-info/RECORD
django_pgsql_interval_field-0.9.4.dist-info/top_level.txt
django_pgsql_interval_field-0.9.4.dist-info/WHEEL
interval/__init__.py
interval/aggregate.py
interval/fields.py
interval/forms.py
interval/models.py
interval/tests.py
interval/locale/de/LC_MESSAGES/django.po
interval/locale/pl/LC_MESSAGES/django.po
interval/static/interval.css
test_project/test_app/__init__.py
test_project/test_app/admin.py
test_project/test_app/models.py
test_project/test_app/tests.py
test_project/test_app/views.py
