Metadata-Version: 2.0
Name: django-pgsql-interval-field
Version: 0.9.4
Summary: Support for PostgreSQL INTERVAL for Django
Home-page: https://github.com/mpasternak/django-interval-field
Author: Michał Pasternak
Author-email: michal.dtz@gmail.com
License: MIT
Platform: UNKNOWN
Requires-Dist: django
Requires-Dist: six
